helix.py
helix_cli-0.1.0.dist-info/METADATA
helix_cli-0.1.0.dist-info/WHEEL
helix_cli-0.1.0.dist-info/entry_points.txt
helix_cli-0.1.0.dist-info/top_level.txt
helix_cli-0.1.0.dist-info/RECORD
