Metadata-Version: 2.4
Name: helix-cli
Version: 0.1.0
Summary: 一个用于管理和查询软件发布版本的命令行工具。
Author-email: Your Name <you@example.com>
Project-URL: Homepage, https://github.com/example/helix
Project-URL: Bug Tracker, https://github.com/example/helix/issues
Classifier: Programming Language :: Python :: 3
Classifier: License :: OSI Approved :: MIT License
Classifier: Operating System :: OS Independent
Classifier: Development Status :: 4 - Beta
Classifier: Environment :: Console
Classifier: Topic :: Software Development :: Build Tools
Requires-Python: >=3.7
Requires-Dist: requests
Requires-Dist: beautifulsoup4
